latz/__init__.py
latz/__main__.py
latz/__version__.py
latz/cli.py
latz/commands/__init__.py
latz/commands/config/__init__.py
latz/commands/config/commands.py
latz/commands/config/validators.py
latz/commands/search.py
latz/config/__init__.py
latz/config/errors.py
latz/config/main.py
latz/config/models.py
latz/constants.py
latz/exceptions.py
latz/fetch.py
latz/image.py
latz/plugins/__init__.py
latz/plugins/hookspec.py
latz/plugins/image/__init__.py
latz/plugins/image/placeholder.py
latz/plugins/image/unsplash.py
latz/plugins/manager.py
latz/py.typed
latz-0.2.1.dist-info/LICENSE
latz-0.2.1.dist-info/WHEEL
latz-0.2.1.dist-info/entry_points.txt
latz-0.2.1.dist-info/METADATA
latz-0.2.1.dist-info/RECORD
