Metadata-Version: 2.1
Name: latz
Version: 0.2.1
Summary: CLI Program for downloading images. Maybe by location too...
License: GNU v3
Author: Travis Hathaway
Author-email: travis.j.hathaway@gmail.com
Requires-Python: >=3.8.1,<4.0.0
Classifier: License :: Other/Proprietary License
Classifier: Programming Language :: Python :: 3
Classifier: Programming Language :: Python :: 3.9
Classifier: Programming Language :: Python :: 3.10
Classifier: Programming Language :: Python :: 3.11
Requires-Dist: Pillow (>=9.3.0,<10.0.0)
Requires-Dist: click (>=8.1.3,<9.0.0)
Requires-Dist: httpx (>=0.23.1,<0.24.0)
Requires-Dist: pluggy (>=1.0.0,<2.0.0)
Requires-Dist: pydantic (>=1.10.7,<2.0.0)
Requires-Dist: rich (>=13.3.3,<14.0.0)
Requires-Dist: rich-click (>=1.6.0,<2.0.0)
